massmail/__init__.py
massmail/__main__.py
massmail-0.1.3.dist-info/entry_points.txt
massmail-0.1.3.dist-info/WHEEL
massmail-0.1.3.dist-info/METADATA
massmail-0.1.3.dist-info/RECORD
