Metadata-Version: 2.1
Name: massmail
Version: 0.1.3
Summary: Mass Mailing via SMTP
Home-page: https://github.com/tz4678/massmail
Author: Sergey M
Author-email: tz4678@gmail.com
Requires-Python: >=3.8,<4.0
Classifier: Programming Language :: Python :: 3
Classifier: Programming Language :: Python :: 3.8
Requires-Dist: click (>=7.1.2,<8.0.0)
